psynet/__init__.py
psynet/api.py
psynet/artifact.py
psynet/asset.py
psynet/audio_mixer.py
psynet/bot.py
psynet/command_line.py
psynet/consent.py
psynet/data.py
psynet/db.py
psynet/deployment_info.py
psynet/end.py
psynet/equipment.py
psynet/error.py
psynet/experiment.py
psynet/field.py
psynet/graphics.py
psynet/js_synth.py
psynet/log.py
psynet/media.py
psynet/modular_page.py
psynet/notifier.py
psynet/page.py
psynet/participant.py
psynet/process.py
psynet/pytest_psynet.py
psynet/recruiters.py
psynet/redis.py
psynet/serialize.py
psynet/sync.py
psynet/timeline.py
psynet/utils.py
psynet/version.py
psynet/dashboard/lucid.py
psynet/dashboard/resources.py
psynet/definitions/__init__.py
psynet/definitions/gold-msi.csv
psynet/demography/__init__.py
psynet/demography/general.py
psynet/demography/gmsi.py
psynet/demography/pei.py
psynet/locales/af/LC_MESSAGES/psynet.po
psynet/locales/am/LC_MESSAGES/psynet.po
psynet/locales/ar/LC_MESSAGES/psynet.po
psynet/locales/as/LC_MESSAGES/psynet.po
psynet/locales/az/LC_MESSAGES/psynet.po
psynet/locales/be/LC_MESSAGES/psynet.po
psynet/locales/bg/LC_MESSAGES/psynet.po
psynet/locales/bn/LC_MESSAGES/psynet.po
psynet/locales/cs/LC_MESSAGES/psynet.po
psynet/locales/da/LC_MESSAGES/psynet.po
psynet/locales/de/LC_MESSAGES/psynet.po
psynet/locales/doi/LC_MESSAGES/psynet.po
psynet/locales/el/LC_MESSAGES/psynet.po
psynet/locales/es/LC_MESSAGES/psynet.po
psynet/locales/et/LC_MESSAGES/psynet.po
psynet/locales/fi/LC_MESSAGES/psynet.po
psynet/locales/fr/LC_MESSAGES/psynet.po
psynet/locales/gu/LC_MESSAGES/psynet.po
psynet/locales/he/LC_MESSAGES/psynet.po
psynet/locales/hi/LC_MESSAGES/psynet.po
psynet/locales/hr/LC_MESSAGES/psynet.po
psynet/locales/hu/LC_MESSAGES/psynet.po
psynet/locales/id/LC_MESSAGES/psynet.po
psynet/locales/is/LC_MESSAGES/psynet.po
psynet/locales/it/LC_MESSAGES/psynet.po
psynet/locales/ja/LC_MESSAGES/psynet.po
psynet/locales/kk/LC_MESSAGES/psynet.po
psynet/locales/km/LC_MESSAGES/psynet.po
psynet/locales/kn/LC_MESSAGES/psynet.po
psynet-13.0.3.dist-info/METADATA
psynet-13.0.3.dist-info/WHEEL
psynet-13.0.3.dist-info/entry_points.txt
psynet-13.0.3.dist-info/licenses/LICENSE
psynet-13.0.3.dist-info/RECORD
