Metadata-Version: 2.4
Name: psynet
Version: 13.0.3
Summary: PsyNet – complex psychological experiments made easy
Project-URL: Changelog, https://gitlab.com/PsyNetDev/PsyNet/-/blob/master/CHANGELOG.md
Project-URL: Documentation, https://psynetdev.gitlab.io/PsyNet/
Project-URL: Homepage, https://www.psynet.dev/
Project-URL: Issues, https://gitlab.com/PsyNetDev/PsyNet/-/issues
Project-URL: Repository, https://gitlab.com/PsyNetDev/PsyNet/
Author-email: Peter Harrison <pmch2@cam.ac.uk>, Frank Höger <frank.hoeger@ae.mpg.de>, Pol van Rijn <pol.van-rijn@ae.mpg.de>, Raja Marjieh <raja.marjieh@princeton.edu>, Nori Jacoby <nori.jacoby@ae.mpg.de>
Maintainer-email: Peter Harrison <pmch2@cam.ac.uk>
License: MIT License
License-File: LICENSE
Keywords: experiments,networks,online,psychology
Classifier: Development Status :: 4 - Beta
Classifier: Framework :: Flask
Classifier: Intended Audience :: Science/Research
Classifier: License :: OSI Approved :: MIT License
Classifier: Operating System :: OS Independent
Classifier: Programming Language :: Python :: 3.10
Classifier: Programming Language :: Python :: 3.11
Classifier: Programming Language :: Python :: 3.12
Classifier: Programming Language :: Python :: 3.13
Requires-Python: >=3.10
Requires-Dist: arabic-reshaper
Requires-Dist: babel
Requires-Dist: dallinger[docker]<12,>=11.5.5
Requires-Dist: debugpy
Requires-Dist: dominate==2.9.1
Requires-Dist: html2text
Requires-Dist: joblib
Requires-Dist: jsonpickle
Requires-Dist: pandas
Requires-Dist: paramiko
Requires-Dist: pillow
Requires-Dist: polib
Requires-Dist: progress
Requires-Dist: pytest
Requires-Dist: pytest-dependency
Requires-Dist: pytest-mock
Requires-Dist: pytest-timeout
Requires-Dist: python-gettext
Requires-Dist: rpdb
Requires-Dist: slack-sdk
Requires-Dist: tenacity
Requires-Dist: tomlkit
Requires-Dist: tqdm
Requires-Dist: yaspin
Provides-Extra: dev
Requires-Dist: beautifulsoup4; extra == 'dev'
Requires-Dist: bump-my-version; extra == 'dev'
Requires-Dist: furo; extra == 'dev'
Requires-Dist: google-cloud-translate; extra == 'dev'
Requires-Dist: isort; extra == 'dev'
Requires-Dist: openai; extra == 'dev'
Requires-Dist: pre-commit; extra == 'dev'
Requires-Dist: sphinx; extra == 'dev'
Requires-Dist: sphinx-autodoc-typehints; extra == 'dev'
Provides-Extra: slack
Requires-Dist: slack-sdk; extra == 'slack'
